yark/__init__.py
yark/builder.py
yark/cli.py
yark/logger.py
yark/parser.py
yark/renderer.py
yark/scanner.py
yark/state.py
yark/updater.py
yark/utils.py
yark_scaffold-1.0.0.dist-info/licenses/LICENSE
yark_scaffold-1.0.0.dist-info/METADATA
yark_scaffold-1.0.0.dist-info/WHEEL
yark_scaffold-1.0.0.dist-info/entry_points.txt
yark_scaffold-1.0.0.dist-info/top_level.txt
yark_scaffold-1.0.0.dist-info/RECORD
