Metadata-Version: 2.4
Name: yark-scaffold
Version: 1.0.0
Summary: A Terraform-inspired YAML-based directory scaffolding tool with state management
Author-email: Youssef Abbih <youssef.abbih@gmail.com>
License: MIT License
Project-URL: Homepage, https://github.com/youssef-abbih/yark
Project-URL: Repository, https://github.com/youssef-abbih/yark
Project-URL: Issues, https://github.com/youssef-abbih/yark/issues
Project-URL: Documentation, https://github.com/youssef-abbih/yark#readme
Keywords: yaml,scaffolding,directory,project-structure,automation,cli,terraform,state-management
Classifier: Development Status :: 5 - Production/Stable
Classifier: Intended Audience :: Developers
Classifier: License :: OSI Approved :: MIT License
Classifier: Programming Language :: Python :: 3
Classifier: Programming Language :: Python :: 3.8
Classifier: Programming Language :: Python :: 3.9
Classifier: Programming Language :: Python :: 3.10
Classifier: Programming Language :: Python :: 3.11
Classifier: Programming Language :: Python :: 3.12
Classifier: Operating System :: OS Independent
Classifier: Topic :: Software Development :: Code Generators
Classifier: Topic :: Software Development :: Libraries :: Python Modules
Classifier: Topic :: Utilities
Requires-Python: >=3.8
License-File: LICENSE
Requires-Dist: pyyaml>=6.0
Requires-Dist: rich>=13.0.0
Provides-Extra: dev
Requires-Dist: pytest>=7.0.0; extra == "dev"
Requires-Dist: pytest-cov>=4.0.0; extra == "dev"
Dynamic: license-file
